AoikLiveReload-0.1.0.dist-info/DESCRIPTION.rst
AoikLiveReload-0.1.0.dist-info/METADATA
AoikLiveReload-0.1.0.dist-info/RECORD
AoikLiveReload-0.1.0.dist-info/WHEEL
AoikLiveReload-0.1.0.dist-info/metadata.json
AoikLiveReload-0.1.0.dist-info/top_level.txt
aoiklivereload/__init__.py
aoiklivereload/aoiklivereload.py
aoiklivereload/demo/__init__.py
aoiklivereload/demo/bottle_demo.py
aoiklivereload/demo/flask_demo.py
aoiklivereload/demo/sanic_demo.py
aoiklivereload/demo/tornado_demo.py
