Metadata-Version: 2.0
Name: AoikLiveReload
Version: 0.1.0
Summary: Detect module file changes and reload the program.
Home-page: https://github.com/AoiKuiyuyou/AoikLiveReload
Author: Aoi.Kuiyuyou
Author-email: aoi.kuiyuyou@google.com
License: MIT
Keywords: live reload
Platform: UNKNOWN
Classifier: Development Status :: 3 - Alpha
Classifier: Intended Audience :: Developers
Classifier: License :: OSI Approved :: MIT License
Classifier: Programming Language :: Python :: 2
Classifier: Programming Language :: Python :: 2.7
Classifier: Programming Language :: Python :: 3
Classifier: Programming Language :: Python :: 3.5
Requires-Dist: watchdog (>=0.8.3)
